meshcat_shapes/__init__.py
meshcat_shapes/frame.py
meshcat_shapes/point.py
meshcat_shapes/textarea.py
meshcat_shapes-0.3.0.dist-info/LICENSE
meshcat_shapes-0.3.0.dist-info/WHEEL
meshcat_shapes-0.3.0.dist-info/METADATA
meshcat_shapes-0.3.0.dist-info/RECORD
