Metadata-Version: 2.1
Name: meshcat-shapes
Version: 0.3.0
Summary: Useful shapes to decorate MeshCat scenes.
Keywords: meshcat,shapes,visualization,robotics
Author-email: Stéphane Caron <stephane.caron@normalesup.org>
Maintainer-email: Stéphane Caron <stephane.caron@normalesup.org>
Requires-Python: >=3.7
Classifier: Development Status :: 4 - Beta
Classifier: Framework :: Robot Framework :: Library
Classifier: Intended Audience :: Developers
Classifier: Intended Audience :: Science/Research
Classifier: License :: OSI Approved :: Apache Software License
Classifier: Operating System :: OS Independent
Classifier: Programming Language :: Python :: 3
Classifier: Programming Language :: Python :: 3.7
Classifier: Programming Language :: Python :: 3.8
Classifier: Programming Language :: Python :: 3.9
Classifier: Programming Language :: Python :: 3.10
Classifier: Topic :: Scientific/Engineering :: Physics
Requires-Dist: meshcat >=0.1.1
Requires-Dist: sphinx ; extra == "doc"
Project-URL: Changelog, https://github.com/stephane-caron/meshcat-shapes/blob/master/CHANGELOG.md
Project-URL: Source, https://github.com/stephane-caron/meshcat-shapes
Project-URL: Tracker, https://github.com/stephane-caron/meshcat-shapes/issues
Provides-Extra: doc
